<?xml version="1.0" encoding="utf-8"?>
<Record Tag="REFR">
  <Flags>0</Flags>
  <FormID ID="0900D187">REFR - 0700D187</FormID>
  <FormVersion>15</FormVersion>
  <CompressionCorrupted>false</CompressionCorrupted>
  <Subrecords>
    <Base Tag="NAME">
      <Reference ID="0007EA27">Ammo22LR</Reference>
    </Base>
    <Count Tag="XCNT">32</Count>
    <PositionRotation Tag="DATA">
      <Position>
        <X>1847.41248</X>
        <Y>2103.17578</Y>
        <Z>1539.56396</Z>
      </Position>
      <Rotation>
        <X>2.61799396E-05</X>
        <Y>0.00480489153</Y>
        <Z>5.29687166</Z>
      </Rotation>
    </PositionRotation>
  </Subrecords>
</Record>