<?xml version="1.0" encoding="utf-8"?>
<Record Tag="REFR">
  <Flags>0</Flags>
  <FormID ID="0C01319F">REFR - 0C01319F</FormID>
  <FormVersion>15</FormVersion>
  <CompressionCorrupted>false</CompressionCorrupted>
  <Subrecords>
    <Base Tag="NAME">
      <Reference ID="0008FFE6">TreeHardwoodStumpMudDirt01</Reference>
    </Base>
    <PositionRotation Tag="DATA">
      <Position>
        <X>-3329.12207</X>
        <Y>-6265.49756</Y>
        <Z>12304.3301</Z>
      </Position>
      <Rotation>
        <X>0.0064472463</X>
        <Y>0.0495830588</Y>
        <Z>1.70016015</Z>
      </Rotation>
    </PositionRotation>
  </Subrecords>
</Record>