<?xml version="1.0" encoding="utf-8"?>
<Record Tag="REFR">
  <Flags>0</Flags>
  <FormID ID="0C013035">REFR - 0C013035</FormID>
  <FormVersion>15</FormVersion>
  <CompressionCorrupted>false</CompressionCorrupted>
  <Subrecords>
    <Base Tag="NAME">
      <Reference ID="06042D03">NeoRmPitRailStraight01</Reference>
    </Base>
    <PositionRotation Tag="DATA">
      <Position>
        <X>-4197.37109</X>
        <Y>-1533.02405</Y>
        <Z>12000</Z>
      </Position>
      <Rotation>
        <X>0</X>
        <Y>0</Y>
        <Z>3.10668945</Z>
      </Rotation>
    </PositionRotation>
  </Subrecords>
</Record>