<?xml version="1.0" encoding="utf-8"?>
<Record Tag="REFR">
  <Flags>0</Flags>
  <FormID ID="0C004B17">REFR - 0C004B17</FormID>
  <FormVersion>15</FormVersion>
  <CompressionCorrupted>false</CompressionCorrupted>
  <Subrecords>
    <Base Tag="NAME">
      <Reference ID="0005B6CE">WhiskeyBottle01Empty01</Reference>
    </Base>
    <PositionRotation Tag="DATA">
      <Position>
        <X>-2485.31763</X>
        <Y>-2681.39404</Y>
        <Z>6921.67139</Z>
      </Position>
      <Rotation>
        <X>4.28978872</X>
        <Y>0.547056019</Y>
        <Z>6.0751195</Z>
      </Rotation>
    </PositionRotation>
  </Subrecords>
</Record>