<?xml version="1.0" encoding="utf-8"?>
<Record Tag="REFR">
  <Flags>0</Flags>
  <FormID ID="0C004B3A">REFR - 0C004B3A</FormID>
  <FormVersion>15</FormVersion>
  <CompressionCorrupted>false</CompressionCorrupted>
  <Subrecords>
    <Base Tag="NAME">
      <Reference ID="000F1E4C">dlc04sodacup02</Reference>
    </Base>
    <PositionRotation Tag="DATA">
      <Position>
        <X>-477.564514</X>
        <Y>-2179.07422</Y>
        <Z>6756.32568</Z>
      </Position>
      <Rotation>
        <X>1.89538217</X>
        <Y>5.86635685</Y>
        <Z>6.20994616</Z>
      </Rotation>
    </PositionRotation>
  </Subrecords>
</Record>