<?xml version="1.0" encoding="utf-8"?>
<Record Tag="REFR">
  <Flags>0</Flags>
  <FormID ID="0C004B29">REFR - 0C004B29</FormID>
  <FormVersion>15</FormVersion>
  <CompressionCorrupted>false</CompressionCorrupted>
  <Subrecords>
    <Base Tag="NAME">
      <Reference ID="000F1E4C">dlc04sodacup02</Reference>
    </Base>
    <PositionRotation Tag="DATA">
      <Position>
        <X>-3311.57373</X>
        <Y>-2031.7666</Y>
        <Z>6954.76855</Z>
      </Position>
      <Rotation>
        <X>4.57610846</X>
        <Y>0.0412142053</Y>
        <Z>0.227526352</Z>
      </Rotation>
    </PositionRotation>
  </Subrecords>
</Record>