<?xml version="1.0" encoding="utf-8"?>
<Record Tag="REFR">
  <Flags>0</Flags>
  <FormID ID="0C00498B">REFR - 0C00498B</FormID>
  <FormVersion>15</FormVersion>
  <CompressionCorrupted>false</CompressionCorrupted>
  <Subrecords>
    <Base Tag="NAME">
      <Reference ID="000F1E4C">dlc04sodacup02</Reference>
    </Base>
    <PositionRotation Tag="DATA">
      <Position>
        <X>-3321.82739</X>
        <Y>-2416.09888</Y>
        <Z>6461.01563</Z>
      </Position>
      <Rotation>
        <X>4.55350971</X>
        <Y>0.737801313</Y>
        <Z>3.03806853</Z>
      </Rotation>
    </PositionRotation>
  </Subrecords>
</Record>