<?xml version="1.0" encoding="utf-8"?>
<Record Tag="REFR">
  <Flags>0</Flags>
  <FormID ID="0C00486E">REFR - 0C00486E</FormID>
  <FormVersion>15</FormVersion>
  <CompressionCorrupted>false</CompressionCorrupted>
  <Subrecords>
    <Base Tag="NAME">
      <Reference ID="00023FB7">FXLightBeam05</Reference>
    </Base>
    <Emittance Tag="XEMI">
      <Reference ID="00062EA3">MetroLightKeyCool</Reference>
    </Emittance>
    <Scale Tag="XSCL">1.00999999</Scale>
    <PositionRotation Tag="DATA">
      <Position>
        <X>-3434.06812</X>
        <Y>-3641.47827</Y>
        <Z>7570.34961</Z>
      </Position>
      <Rotation>
        <X>0.121542983</X>
        <Y>0.598564148</Y>
        <Z>0.0332223438</Z>
      </Rotation>
    </PositionRotation>
  </Subrecords>
</Record>