<?xml version="1.0" encoding="utf-8"?>
<Record Tag="REFR">
  <Flags>0</Flags>
  <FormID ID="0C0048EC">REFR - 0C0048EC</FormID>
  <FormVersion>15</FormVersion>
  <CompressionCorrupted>false</CompressionCorrupted>
  <Subrecords>
    <Base Tag="NAME">
      <Reference ID="0005B6CA">TinCan02</Reference>
    </Base>
    <PositionRotation Tag="DATA">
      <Position>
        <X>-2060.45215</X>
        <Y>-769.724304</Y>
        <Z>6404.52734</Z>
      </Position>
      <Rotation>
        <X>1.39900875</X>
        <Y>6.11011839</Y>
        <Z>2.25564075</Z>
      </Rotation>
    </PositionRotation>
  </Subrecords>
</Record>