<?xml version="1.0" encoding="utf-8"?>
<Record Tag="REFR">
  <Flags>0</Flags>
  <FormID ID="060A9973">REFR - 060A9973</FormID>
  <FormVersion>15</FormVersion>
  <CompressionCorrupted>false</CompressionCorrupted>
  <Subrecords>
    <Base Tag="NAME">
      <Reference ID="0C00CD2F">TTWFungus05ACTIVATOR</Reference>
    </Base>
    <Scale Tag="XSCL">0.949999988</Scale>
    <PositionRotation Tag="DATA">
      <Position>
        <X>3630.94678</X>
        <Y>2717.01294</Y>
        <Z>3214.49219</Z>
      </Position>
      <Rotation>
        <X>6.2011776</X>
        <Y>0.06806086</Y>
        <Z>5.34631538</Z>
      </Rotation>
    </PositionRotation>
  </Subrecords>
</Record>