<?xml version="1.0" encoding="utf-8"?>
<Record Tag="REFR">
  <Flags>0</Flags>
  <FormID ID="060A6608">REFR - 060A6608</FormID>
  <FormVersion>15</FormVersion>
  <CompressionCorrupted>false</CompressionCorrupted>
  <Subrecords>
    <Base Tag="NAME">
      <Reference ID="0C00CD2E">TTWFungus04ACTIVATOR</Reference>
    </Base>
    <Scale Tag="XSCL">1.25</Scale>
    <PositionRotation Tag="DATA">
      <Position>
        <X>4008.46191</X>
        <Y>795.922668</Y>
        <Z>3288.03638</Z>
      </Position>
      <Rotation>
        <X>0.400001526</X>
        <Y>0</Y>
        <Z>0</Z>
      </Rotation>
    </PositionRotation>
  </Subrecords>
</Record>