<?xml version="1.0" encoding="utf-8"?>
<Record Tag="REFR">
  <Flags>0</Flags>
  <FormID ID="0C013682">REFR - 0C013682</FormID>
  <FormVersion>15</FormVersion>
  <CompressionCorrupted>false</CompressionCorrupted>
  <Subrecords>
    <Base Tag="NAME">
      <Reference ID="0006FCEB">BLD03Column03</Reference>
    </Base>
    <PositionRotation Tag="DATA">
      <Position>
        <X>-8670.22168</X>
        <Y>-8065.22949</Y>
        <Z>12302.3643</Z>
      </Position>
      <Rotation>
        <X>1.52238786</X>
        <Y>5.71779299</Y>
        <Z>2.26112461</Z>
      </Rotation>
    </PositionRotation>
  </Subrecords>
</Record>