<?xml version="1.0" encoding="utf-8"?>
<Record Tag="REFR">
  <Flags>0</Flags>
  <FormID ID="0C0133FF">REFR - 0C0133FF</FormID>
  <FormVersion>15</FormVersion>
  <CompressionCorrupted>false</CompressionCorrupted>
  <Subrecords>
    <Base Tag="NAME">
      <Reference ID="0001999E">CementPlanterRd01</Reference>
    </Base>
    <PositionRotation Tag="DATA">
      <Position>
        <X>1336.97314</X>
        <Y>-2032.85596</Y>
        <Z>12360.7891</Z>
      </Position>
      <Rotation>
        <X>0</X>
        <Y>0</Y>
        <Z>0</Z>
      </Rotation>
    </PositionRotation>
  </Subrecords>
</Record>