<?xml version="1.0" encoding="utf-8"?>
<Record Tag="REFR">
  <Flags>0</Flags>
  <FormID ID="0C0022EB">REFR - 0C0022EB</FormID>
  <FormVersion>15</FormVersion>
  <CompressionCorrupted>false</CompressionCorrupted>
  <Subrecords>
    <Base Tag="NAME">
      <Reference ID="00022103">NukaColaBottle</Reference>
    </Base>
    <PositionRotation Tag="DATA">
      <Position>
        <X>-2599.87695</X>
        <Y>-517.363586</Y>
        <Z>6463.52783</Z>
      </Position>
      <Rotation>
        <X>4.70755291</X>
        <Y>5.25624037</Y>
        <Z>0.00335452287</Z>
      </Rotation>
    </PositionRotation>
  </Subrecords>
</Record>