<?xml version="1.0" encoding="utf-8"?>
<Record Tag="REFR">
  <Flags>0</Flags>
  <FormID ID="0C002A39">REFR - 0C002A39</FormID>
  <FormVersion>15</FormVersion>
  <CompressionCorrupted>false</CompressionCorrupted>
  <Subrecords>
    <Base Tag="NAME">
      <Reference ID="00025751">DefaultFireBarrelIdleMarker</Reference>
    </Base>
    <PositionRotation Tag="DATA">
      <Position>
        <X>-3941.99976</X>
        <Y>-1906.052</Y>
        <Z>6473.91162</Z>
      </Position>
      <Rotation>
        <X>0</X>
        <Y>0</Y>
        <Z>1.40000188</Z>
      </Rotation>
    </PositionRotation>
  </Subrecords>
</Record>