<?xml version="1.0" encoding="utf-8"?>
<Record Tag="REFR">
  <Flags>0</Flags>
  <FormID ID="0C002A50">REFR - 0C002A50</FormID>
  <FormVersion>15</FormVersion>
  <CompressionCorrupted>false</CompressionCorrupted>
  <Subrecords>
    <Base Tag="NAME">
      <Reference ID="0C001E25">TTWTicketTerminal01</Reference>
    </Base>
    <PositionRotation Tag="DATA">
      <Position>
        <X>-3197.79346</X>
        <Y>-2718.75049</Y>
        <Z>6970.35693</Z>
      </Position>
      <Rotation>
        <X>0</X>
        <Y>0</Y>
        <Z>0</Z>
      </Rotation>
    </PositionRotation>
  </Subrecords>
</Record>