<?xml version="1.0" encoding="utf-8"?>
<Record Tag="REFR">
  <Flags>0</Flags>
  <FormID ID="0C0027E2">REFR - 0C0027E2</FormID>
  <FormVersion>15</FormVersion>
  <CompressionCorrupted>false</CompressionCorrupted>
  <Subrecords>
    <Base Tag="NAME">
      <Reference ID="00022103">NukaColaBottle</Reference>
    </Base>
    <PositionRotation Tag="DATA">
      <Position>
        <X>-442.008972</X>
        <Y>-3353.82251</Y>
        <Z>6779.89209</Z>
      </Position>
      <Rotation>
        <X>4.92790556</X>
        <Y>0.765100002</Y>
        <Z>3.12984657</Z>
      </Rotation>
    </PositionRotation>
  </Subrecords>
</Record>