<?xml version="1.0" encoding="utf-8"?>
<Record Tag="REFR">
  <Flags>0</Flags>
  <FormID ID="0C00285E">REFR - 0C00285E</FormID>
  <FormVersion>15</FormVersion>
  <CompressionCorrupted>false</CompressionCorrupted>
  <Subrecords>
    <Base Tag="NAME">
      <Reference ID="000340BC">Spoon01</Reference>
    </Base>
    <PositionRotation Tag="DATA">
      <Position>
        <X>-126.360413</X>
        <Y>-2516.15454</Y>
        <Z>6798.21045</Z>
      </Position>
      <Rotation>
        <X>5.29066563</X>
        <Y>1.06673646</Y>
        <Z>2.37642813</Z>
      </Rotation>
    </PositionRotation>
  </Subrecords>
</Record>