<?xml version="1.0" encoding="utf-8"?>
<Record Tag="REFR">
  <Flags>0</Flags>
  <FormID ID="0C002875">REFR - 0C002875</FormID>
  <FormVersion>15</FormVersion>
  <CompressionCorrupted>false</CompressionCorrupted>
  <Subrecords>
    <Base Tag="NAME">
      <Reference ID="0002216A">MilkCrate01</Reference>
    </Base>
    <PositionRotation Tag="DATA">
      <Position>
        <X>-7.85632801</X>
        <Y>-2678.9917</Y>
        <Z>6764.50781</Z>
      </Position>
      <Rotation>
        <X>3.14649868</X>
        <Y>6.27919912</Y>
        <Z>6.25566483</Z>
      </Rotation>
    </PositionRotation>
  </Subrecords>
</Record>