<?xml version="1.0" encoding="utf-8"?>
<Record Tag="REFR">
  <Flags>0</Flags>
  <FormID ID="0C002505">REFR - 0C002505</FormID>
  <FormVersion>15</FormVersion>
  <CompressionCorrupted>false</CompressionCorrupted>
  <Subrecords>
    <Base Tag="NAME">
      <Reference ID="00014E7E">Barrel01</Reference>
    </Base>
    <PositionRotation Tag="DATA">
      <Position>
        <X>-2344.83838</X>
        <Y>-5648.41357</Y>
        <Z>6416.01123</Z>
      </Position>
      <Rotation>
        <X>6.28305435</X>
        <Y>6.28031588</Y>
        <Z>0.000202458192</Z>
      </Rotation>
    </PositionRotation>
  </Subrecords>
</Record>