<?xml version="1.0" encoding="utf-8"?>
<Record Tag="CONT">
  <Flags>NavMeshGenerationBoundingBox</Flags>
  <FormID ID="06019F3C">MailDropbox01NewDC</FormID>
  <FormVersion>15</FormVersion>
  <CompressionCorrupted>false</CompressionCorrupted>
  <Subrecords>
    <EditorID Tag="EDID">MailDropbox01NewDC</EditorID>
    <ObjectBounds Tag="OBND">
      <Point1>
        <X>-27</X>
        <Y>-26</Y>
        <Z>-47</Z>
      </Point1>
      <Point2>
        <X>27</X>
        <Y>26</Y>
        <Z>47</Z>
      </Point2>
    </ObjectBounds>
    <Name Tag="FULL">Mail Dropbox</Name>
    <Model>
      <FileName Tag="MODL">Architecture\Urban\StreetDressing\MailDropbox01.NIF</FileName>
      <TextureFileHash Tag="MODT">sbANbT03c6gxMA1tQjdzqG5hG3QM51Zc7t8PbT4HxHZuXw9tQwfEdm5hG3QM51Zc898PbT4HxHZzXw9tQwfEdm5hG3QM51Zc</TextureFileHash>
    </Model>
    <Contents>
      <Item>
        <Data Tag="CNTO">
          <Item ID="0003787B">ClutterSchool15</Item>
          <Count>1</Count>
        </Data>
      </Item>
      <Item>
        <Data Tag="CNTO">
          <Item ID="06037875">ClutterHousehold15DC</Item>
          <Count>1</Count>
        </Data>
      </Item>
    </Contents>
    <Data Tag="DATA">
      <Flags>0</Flags>
      <Weight>0</Weight>
    </Data>
    <Random_LoopingSound Tag="RNAM">
      <Reference ID="0014CBD9">EMTSandOnMetal</Reference>
    </Random_LoopingSound>
  </Subrecords>
</Record>