<?xml version="1.0" encoding="utf-8"?>
<Record Tag="REFR">
  <Flags>0</Flags>
  <FormID ID="0C002DD1">REFR - 0C002DD1</FormID>
  <FormVersion>15</FormVersion>
  <CompressionCorrupted>false</CompressionCorrupted>
  <Subrecords>
    <Base Tag="NAME">
      <Reference ID="0003406C">CoffeeMug01</Reference>
    </Base>
    <PositionRotation Tag="DATA">
      <Position>
        <X>133.442368</X>
        <Y>-3426.12793</Y>
        <Z>7196.34326</Z>
      </Position>
      <Rotation>
        <X>1.5926199</X>
        <Y>0.0892159939</Y>
        <Z>2.02364635</Z>
      </Rotation>
    </PositionRotation>
  </Subrecords>
</Record>