<?xml version="1.0" encoding="utf-8"?>
<Record Tag="REFR">
  <Flags>0</Flags>
  <FormID ID="0C00379F">REFR - 0C00379F</FormID>
  <FormVersion>15</FormVersion>
  <CompressionCorrupted>false</CompressionCorrupted>
  <Subrecords>
    <Base Tag="NAME">
      <Reference ID="000F1E4C">dlc04sodacup02</Reference>
    </Base>
    <PositionRotation Tag="DATA">
      <Position>
        <X>2354.99805</X>
        <Y>1037.86047</Y>
        <Z>7459.90234</Z>
      </Position>
      <Rotation>
        <X>1.64316297</X>
        <Y>6.1796155</Y>
        <Z>3.39221501</Z>
      </Rotation>
    </PositionRotation>
  </Subrecords>
</Record>