<?xml version="1.0" encoding="utf-8"?>
<Record Tag="REFR">
  <Flags>0</Flags>
  <FormID ID="0C0035FC">REFR - 0C0035FC</FormID>
  <FormVersion>15</FormVersion>
  <CompressionCorrupted>false</CompressionCorrupted>
  <Subrecords>
    <Base Tag="NAME">
      <Reference ID="0005C65E">DrinkToiletBrokeSTATIC04</Reference>
    </Base>
    <PositionRotation Tag="DATA">
      <Position>
        <X>623.805359</X>
        <Y>-3.03958797</Y>
        <Z>7138.32129</Z>
      </Position>
      <Rotation>
        <X>0.569136143</X>
        <Y>0.11742226</Y>
        <Z>5.58187866</Z>
      </Rotation>
    </PositionRotation>
  </Subrecords>
</Record>