<?xml version="1.0" encoding="utf-8"?>
<Record Tag="REFR">
  <Flags>0</Flags>
  <FormID ID="0C003959">REFR - 0C003959</FormID>
  <FormVersion>15</FormVersion>
  <CompressionCorrupted>false</CompressionCorrupted>
  <Subrecords>
    <Base Tag="NAME">
      <Reference ID="0005B6CA">TinCan02</Reference>
    </Base>
    <PositionRotation Tag="DATA">
      <Position>
        <X>2088.51733</X>
        <Y>-2173.17676</Y>
        <Z>7143.08838</Z>
      </Position>
      <Rotation>
        <X>4.59163475</X>
        <Y>6.16683102</Y>
        <Z>0.205606773</Z>
      </Rotation>
    </PositionRotation>
  </Subrecords>
</Record>