<?xml version="1.0" encoding="utf-8"?>
<Record Tag="REFR">
  <Flags>0</Flags>
  <FormID ID="0C002DD7">REFR - 0C002DD7</FormID>
  <FormVersion>15</FormVersion>
  <CompressionCorrupted>false</CompressionCorrupted>
  <Subrecords>
    <Base Tag="NAME">
      <Reference ID="0003406C">CoffeeMug01</Reference>
    </Base>
    <PositionRotation Tag="DATA">
      <Position>
        <X>461.856628</X>
        <Y>-3436.00879</Y>
        <Z>7152.66309</Z>
      </Position>
      <Rotation>
        <X>1.58632457</X>
        <Y>0.575112164</Y>
        <Z>0.915786505</Z>
      </Rotation>
    </PositionRotation>
  </Subrecords>
</Record>