<?xml version="1.0" encoding="utf-8"?>
<Record Tag="REFR">
  <Flags>0</Flags>
  <FormID ID="0C002CFE">REFR - 0C002CFE</FormID>
  <FormVersion>15</FormVersion>
  <CompressionCorrupted>false</CompressionCorrupted>
  <Subrecords>
    <Base Tag="NAME">
      <Reference ID="0003406C">CoffeeMug01</Reference>
    </Base>
    <PositionRotation Tag="DATA">
      <Position>
        <X>268.978302</X>
        <Y>-1985.04834</Y>
        <Z>7214.05029</Z>
      </Position>
      <Rotation>
        <X>1.55644274</X>
        <Y>5.04526186</Y>
        <Z>4.18392754</Z>
      </Rotation>
    </PositionRotation>
  </Subrecords>
</Record>