<?xml version="1.0" encoding="utf-8"?>
<Record Tag="REFR">
  <Flags>0</Flags>
  <FormID ID="0C00376D">REFR - 0C00376D</FormID>
  <FormVersion>15</FormVersion>
  <CompressionCorrupted>false</CompressionCorrupted>
  <Subrecords>
    <Base Tag="NAME">
      <Reference ID="000F1E4C">dlc04sodacup02</Reference>
    </Base>
    <PositionRotation Tag="DATA">
      <Position>
        <X>1843.95068</X>
        <Y>2226.12451</Y>
        <Z>7151.72021</Z>
      </Position>
      <Rotation>
        <X>2.57954264</X>
        <Y>0.894364297</Y>
        <Z>0.801331282</Z>
      </Rotation>
    </PositionRotation>
  </Subrecords>
</Record>