<?xml version="1.0" encoding="utf-8"?>
<Record Tag="REFR">
  <Flags>0</Flags>
  <FormID ID="0C002D85">REFR - 0C002D85</FormID>
  <FormVersion>15</FormVersion>
  <CompressionCorrupted>false</CompressionCorrupted>
  <Subrecords>
    <Base Tag="NAME">
      <Reference ID="0005B63F">Plate03</Reference>
    </Base>
    <PositionRotation Tag="DATA">
      <Position>
        <X>624.381836</X>
        <Y>-2956.25024</Y>
        <Z>7192.63525</Z>
      </Position>
      <Rotation>
        <X>0</X>
        <Y>6.28226709</Y>
        <Z>4.71238899</Z>
      </Rotation>
    </PositionRotation>
  </Subrecords>
</Record>