<?xml version="1.0" encoding="utf-8"?>
<Record Tag="REFR">
  <Flags>0</Flags>
  <FormID ID="0C002D0E">REFR - 0C002D0E</FormID>
  <FormVersion>15</FormVersion>
  <CompressionCorrupted>false</CompressionCorrupted>
  <Subrecords>
    <Base Tag="NAME">
      <Reference ID="0003406C">CoffeeMug01</Reference>
    </Base>
    <PositionRotation Tag="DATA">
      <Position>
        <X>136.549789</X>
        <Y>-2119.37061</Y>
        <Z>7207.81104</Z>
      </Position>
      <Rotation>
        <X>4.29519749</X>
        <Y>5.17882109</Y>
        <Z>1.63462651</Z>
      </Rotation>
    </PositionRotation>
  </Subrecords>
</Record>