<?xml version="1.0" encoding="utf-8"?>
<Record Tag="REFR">
  <Flags>0</Flags>
  <FormID ID="0C002B84">REFR - 0C002B84</FormID>
  <FormVersion>15</FormVersion>
  <CompressionCorrupted>false</CompressionCorrupted>
  <Subrecords>
    <Base Tag="NAME">
      <Reference ID="000F250B">DLC05RubblePile04</Reference>
    </Base>
    <Scale Tag="XSCL">1.25</Scale>
    <PositionRotation Tag="DATA">
      <Position>
        <X>5756.43994</X>
        <Y>-2019.9071</Y>
        <Z>6863.16455</Z>
      </Position>
      <Rotation>
        <X>0.0999899134</X>
        <Y>0.100000381</Y>
        <Z>2.51002073</Z>
      </Rotation>
    </PositionRotation>
  </Subrecords>
</Record>