<?xml version="1.0" encoding="utf-8"?>
<Record Tag="REFR">
  <Flags>0</Flags>
  <FormID ID="0C002AF7">REFR - 0C002AF7</FormID>
  <FormVersion>15</FormVersion>
  <CompressionCorrupted>false</CompressionCorrupted>
  <Subrecords>
    <Base Tag="NAME">
      <Reference ID="0005B6CA">TinCan02</Reference>
    </Base>
    <PositionRotation Tag="DATA">
      <Position>
        <X>4553.72803</X>
        <Y>-2650.79492</Y>
        <Z>6758.39746</Z>
      </Position>
      <Rotation>
        <X>4.68965244</X>
        <Y>6.10562754</Y>
        <Z>1.04287088</Z>
      </Rotation>
    </PositionRotation>
  </Subrecords>
</Record>