<?xml version="1.0" encoding="utf-8"?>
<Record Tag="REFR">
  <Flags>VisibleWhenDistant</Flags>
  <FormID ID="0C013BD7">REFR - 0C013BD7</FormID>
  <FormVersion>15</FormVersion>
  <CompressionCorrupted>false</CompressionCorrupted>
  <Subrecords>
    <Base Tag="NAME">
      <Reference ID="0400363A">BgBld03</Reference>
    </Base>
    <PositionRotation Tag="DATA">
      <Position>
        <X>-9068.27539</X>
        <Y>10510.5654</Y>
        <Z>13527.5596</Z>
      </Position>
      <Rotation>
        <X>6.21554327</X>
        <Y>0.0583428666</Y>
        <Z>3.26114082</Z>
      </Rotation>
    </PositionRotation>
  </Subrecords>
</Record>