<?xml version="1.0" encoding="utf-8"?>
<Record Tag="REFR">
  <Flags>0</Flags>
  <FormID ID="0C0132AC">REFR - 0C0132AC</FormID>
  <FormVersion>15</FormVersion>
  <CompressionCorrupted>false</CompressionCorrupted>
  <Subrecords>
    <Base Tag="NAME">
      <Reference ID="00028E1D">TenPenSidewalkChunk01</Reference>
    </Base>
    <PositionRotation Tag="DATA">
      <Position>
        <X>-787.665283</X>
        <Y>275.023041</Y>
        <Z>12296.1895</Z>
      </Position>
      <Rotation>
        <X>0.239008874</X>
        <Y>0.00441742828</Y>
        <Z>0.889725208</Z>
      </Rotation>
    </PositionRotation>
  </Subrecords>
</Record>