<?xml version="1.0" encoding="utf-8"?>
<Record Tag="NAVM">
  <Flags>0</Flags>
  <FormID ID="06071AF8">NAVM - 06071AF8</FormID>
  <FormVersion>15</FormVersion>
  <CompressionCorrupted>false</CompressionCorrupted>
  <Subrecords>
    <Version Tag="NVER">11</Version>
    <Data Tag="DATA">
      <Cell ID="06000C81">AnchorageWMExterior</Cell>
      <VertexCount>9</VertexCount>
      <TriangleCount>7</TriangleCount>
      <ExternalConnectionsCount>4</ExternalConnectionsCount>
      <NVCACount>0</NVCACount>
      <DoorsCount>0</DoorsCount>
    </Data>
    <Vertices Tag="NVVX">AAAwRwAAwcYAICZGDOQuR9JSwcZ7PSVG/t0vR23CwcYAUCZG6YIvRwAAwMYAgCZGAAAwRwAAwMYAICZGzgIvRwAAwMYGjCZGTCwuRwAAwMYooCZGKdovRy/twcawVyZG/v0vR23CwcYAaCZG</Vertices>
    <Triangles Tag="NVTR">AAABAAIAAQAFAAYAAAgAAAAAAwABAAIAAwAAAAAIAAAAAAQAAwAAAAEAAQADCAAAAQADAAUAAQADAAQAAggAAAUABgABAAIA//8DAAEIAAACAAEABwAAAP////8ACAAAAgAIAAAA/////wAAAAgAAA==</Triangles>
    <Grid Tag="NVGD">AQAAAADa6UOAl3ZDTCwuRy/twcZ7PSVGAAAwRwAAwMYooCZGBwAAAAEAAgADAAQABQAGAA==</Grid>
    <ExternalConnections Tag="NVEX">
      <ExternalConnections>
        <ExternalConnection>
          <Unknown>AAAAAA==</Unknown>
          <NavigationMesh ID="060C38E8">NAVM - 060C38E8</NavigationMesh>
          <Triangle>408</Triangle>
        </ExternalConnection>
        <ExternalConnection>
          <Unknown>AAAAAA==</Unknown>
          <NavigationMesh ID="0607213B">NAVM - 0607213B</NavigationMesh>
          <Triangle>6</Triangle>
        </ExternalConnection>
        <ExternalConnection>
          <Unknown>AAAAAA==</Unknown>
          <NavigationMesh ID="0607213B">NAVM - 0607213B</NavigationMesh>
          <Triangle>115</Triangle>
        </ExternalConnection>
        <ExternalConnection>
          <Unknown>AAAAAA==</Unknown>
          <NavigationMesh ID="0607213B">NAVM - 0607213B</NavigationMesh>
          <Triangle>116</Triangle>
        </ExternalConnection>
      </ExternalConnections>
    </ExternalConnections>
  </Subrecords>
</Record>