<?xml version="1.0" encoding="utf-8"?>
<Record Tag="REFR">
  <Flags>0</Flags>
  <FormID ID="0C00CD8E">REFR - 0C00CD8E</FormID>
  <FormVersion>15</FormVersion>
  <CompressionCorrupted>false</CompressionCorrupted>
  <Subrecords>
    <Base Tag="NAME">
      <Reference ID="0002210D">MedicalBrace</Reference>
    </Base>
    <PositionRotation Tag="DATA">
      <Position>
        <X>3326.41162</X>
        <Y>2367.30029</Y>
        <Z>315.246399</Z>
      </Position>
      <Rotation>
        <X>4.18879026E-05</X>
        <Y>0.00176452787</Y>
        <Z>5.35912085</Z>
      </Rotation>
    </PositionRotation>
  </Subrecords>
</Record>