<?xml version="1.0" encoding="utf-8"?>
<Record Tag="REFR">
  <Flags>0</Flags>
  <FormID ID="09008EC9">REFR - 07008EC9</FormID>
  <FormVersion>15</FormVersion>
  <CompressionCorrupted>false</CompressionCorrupted>
  <Subrecords>
    <Base Tag="NAME">
      <Reference ID="0C00CD2F">TTWFungus05ACTIVATOR</Reference>
    </Base>
    <Scale Tag="XSCL">0.409999996</Scale>
    <PositionRotation Tag="DATA">
      <Position>
        <X>2829.90015</X>
        <Y>951.734192</Y>
        <Z>10749.5068</Z>
      </Position>
      <Rotation>
        <X>6.09370899</X>
        <Y>5.92876148</Y>
        <Z>5.21722031</Z>
      </Rotation>
    </PositionRotation>
  </Subrecords>
</Record>