<?xml version="1.0" encoding="utf-8"?>
<Record Tag="REFR">
  <Flags>0</Flags>
  <FormID ID="0C009BC8">REFR - 0C009BC8</FormID>
  <FormVersion>15</FormVersion>
  <CompressionCorrupted>false</CompressionCorrupted>
  <Subrecords>
    <Base Tag="NAME">
      <Reference ID="0013B2B1">ScrapElectronics</Reference>
    </Base>
    <PositionRotation Tag="DATA">
      <Position>
        <X>3463.26978</X>
        <Y>-8290.48145</Y>
        <Z>-258.322968</Z>
      </Position>
      <Rotation>
        <X>0.00173136662</X>
        <Y>0.00105417892</Y>
        <Z>2.49825907</Z>
      </Rotation>
    </PositionRotation>
  </Subrecords>
</Record>