<?xml version="1.0" encoding="utf-8"?>
<Record Tag="REFR">
  <Flags>0</Flags>
  <FormID ID="0C001EAA">REFR - 0C001EAA</FormID>
  <FormVersion>15</FormVersion>
  <CompressionCorrupted>false</CompressionCorrupted>
  <Subrecords>
    <Base Tag="NAME">
      <Reference ID="0005B63A">Knife02</Reference>
    </Base>
    <PositionRotation Tag="DATA">
      <Position>
        <X>1914.16003</X>
        <Y>190.277451</Y>
        <Z>9830.02344</Z>
      </Position>
      <Rotation>
        <X>6.05724907</X>
        <Y>6.22177744</Y>
        <Z>2.25848913</Z>
      </Rotation>
    </PositionRotation>
  </Subrecords>
</Record>