<?xml version="1.0" encoding="utf-8"?>
<Record Tag="REFR">
  <Flags>0</Flags>
  <FormID ID="0C013798">REFR - 0C013798</FormID>
  <FormVersion>15</FormVersion>
  <CompressionCorrupted>false</CompressionCorrupted>
  <Subrecords>
    <Base Tag="NAME">
      <Reference ID="0006EECE">GoreBagContainer02</Reference>
    </Base>
    <PositionRotation Tag="DATA">
      <Position>
        <X>-10634.0635</X>
        <Y>-11134.8086</Y>
        <Z>12428.6592</Z>
      </Position>
      <Rotation>
        <X>6.12551594</X>
        <Y>6.1958437</Y>
        <Z>5.04761076</Z>
      </Rotation>
    </PositionRotation>
  </Subrecords>
</Record>