<?xml version="1.0" encoding="utf-8"?>
<Record Tag="REFR">
  <Flags>0</Flags>
  <FormID ID="0C013BAB">REFR - 0C013BAB</FormID>
  <FormVersion>15</FormVersion>
  <CompressionCorrupted>false</CompressionCorrupted>
  <Subrecords>
    <Base Tag="NAME">
      <Reference ID="000213F2">SandbagStraight</Reference>
    </Base>
    <PositionRotation Tag="DATA">
      <Position>
        <X>-2157.11084</X>
        <Y>-14180.0762</Y>
        <Z>12366.6035</Z>
      </Position>
      <Rotation>
        <X>0</X>
        <Y>0</Y>
        <Z>6.23318529</Z>
      </Rotation>
    </PositionRotation>
  </Subrecords>
</Record>