<?xml version="1.0" encoding="utf-8"?>
<Record Tag="REFR">
  <Flags>0</Flags>
  <FormID ID="0C013B90">REFR - 0C013B90</FormID>
  <FormVersion>15</FormVersion>
  <CompressionCorrupted>false</CompressionCorrupted>
  <Subrecords>
    <Base Tag="NAME">
      <Reference ID="00022104">TinCan01</Reference>
    </Base>
    <PositionRotation Tag="DATA">
      <Position>
        <X>-1164.87439</X>
        <Y>-13804.0088</Y>
        <Z>12354.5527</Z>
      </Position>
      <Rotation>
        <X>1.68052173</X>
        <Y>0.130943328</Y>
        <Z>1.05389965</Z>
      </Rotation>
    </PositionRotation>
  </Subrecords>
</Record>