<?xml version="1.0" encoding="utf-8"?>
<Record Tag="REFR">
  <Flags>0</Flags>
  <FormID ID="060B1FC9">REFR - 060B1FC9</FormID>
  <FormVersion>15</FormVersion>
  <CompressionCorrupted>false</CompressionCorrupted>
  <Subrecords>
    <Base Tag="NAME">
      <Reference ID="0007EA27">Ammo22LR</Reference>
    </Base>
    <Count Tag="XCNT">19</Count>
    <PositionRotation Tag="DATA">
      <Position>
        <X>2029.04065</X>
        <Y>-2158.21802</Y>
        <Z>730.2995</Z>
      </Position>
      <Rotation>
        <X>6.28223944</X>
        <Y>6.28204727</Y>
        <Z>4.97745752</Z>
      </Rotation>
    </PositionRotation>
  </Subrecords>
</Record>