<?xml version="1.0" encoding="utf-8"?>
<Record Tag="REFR">
  <Flags>0</Flags>
  <FormID ID="0C013C81">REFR - 0C013C81</FormID>
  <FormVersion>15</FormVersion>
  <CompressionCorrupted>false</CompressionCorrupted>
  <Subrecords>
    <Base Tag="NAME">
      <Reference ID="000F1ADD">Planter01</Reference>
    </Base>
    <PositionRotation Tag="DATA">
      <Position>
        <X>1605.99841</X>
        <Y>202.767273</Y>
        <Z>12587.54</Z>
      </Position>
      <Rotation>
        <X>0.0250227861</X>
        <Y>0.00245044217</Y>
        <Z>3.37335849</Z>
      </Rotation>
    </PositionRotation>
  </Subrecords>
</Record>