<?xml version="1.0" encoding="utf-8"?>
<Record Tag="REFR">
  <Flags>0</Flags>
  <FormID ID="0C00CD68">REFR - 0C00CD68</FormID>
  <FormVersion>15</FormVersion>
  <CompressionCorrupted>false</CompressionCorrupted>
  <Subrecords>
    <Base Tag="NAME">
      <Reference ID="000E2C6F">NVAntivenom</Reference>
    </Base>
    <PositionRotation Tag="DATA">
      <Position>
        <X>-274.341034</X>
        <Y>11566.9805</Y>
        <Z>-820.077881</Z>
      </Position>
      <Rotation>
        <X>0.000567232026</X>
        <Y>0.000466002908</Y>
        <Z>0</Z>
      </Rotation>
    </PositionRotation>
  </Subrecords>
</Record>