<?xml version="1.0" encoding="utf-8"?>
<Record Tag="REFR">
  <Flags>0</Flags>
  <FormID ID="0C01381D">REFR - 0C01381D</FormID>
  <FormVersion>15</FormVersion>
  <CompressionCorrupted>false</CompressionCorrupted>
  <Subrecords>
    <Base Tag="NAME">
      <Reference ID="0005F347">ParkingBlock01</Reference>
    </Base>
    <PositionRotation Tag="DATA">
      <Position>
        <X>-7423.52637</X>
        <Y>-11437.7236</Y>
        <Z>12305.9277</Z>
      </Position>
      <Rotation>
        <X>0</X>
        <Y>0</Y>
        <Z>0.699999213</Z>
      </Rotation>
    </PositionRotation>
  </Subrecords>
</Record>