<?xml version="1.0" encoding="utf-8"?>
<Record Tag="REFR">
  <Flags>0</Flags>
  <FormID ID="0C012589">REFR - 0C012589</FormID>
  <FormVersion>15</FormVersion>
  <CompressionCorrupted>false</CompressionCorrupted>
  <Subrecords>
    <Base Tag="NAME">
      <Reference ID="0002210E">PaintGun</Reference>
    </Base>
    <PositionRotation Tag="DATA">
      <Position>
        <X>2927.88623</X>
        <Y>4445.2832</Y>
        <Z>6933.66064</Z>
      </Position>
      <Rotation>
        <X>0.0456717759</X>
        <Y>6.08571005</Y>
        <Z>1.49400187</Z>
      </Rotation>
    </PositionRotation>
  </Subrecords>
</Record>