<?xml version="1.0" encoding="utf-8"?>
<Record Tag="REFR">
  <Flags>0</Flags>
  <FormID ID="0C0128C6">REFR - 0C0128C6</FormID>
  <FormVersion>15</FormVersion>
  <CompressionCorrupted>false</CompressionCorrupted>
  <Subrecords>
    <Base Tag="NAME">
      <Reference ID="0003406F">BoxDetergent</Reference>
    </Base>
    <PositionRotation Tag="DATA">
      <Position>
        <X>5352.05078</X>
        <Y>2235.42432</Y>
        <Z>5937.76904</Z>
      </Position>
      <Rotation>
        <X>0.106287062</X>
        <Y>0.44466278</Y>
        <Z>0.237090766</Z>
      </Rotation>
    </PositionRotation>
  </Subrecords>
</Record>