<?xml version="1.0" encoding="utf-8"?>
<Record Tag="REFR">
  <Flags>0</Flags>
  <FormID ID="0C012860">REFR - 0C012860</FormID>
  <FormVersion>15</FormVersion>
  <CompressionCorrupted>false</CompressionCorrupted>
  <Subrecords>
    <Base Tag="NAME">
      <Reference ID="000A9E6C">BurnedBook05</Reference>
    </Base>
    <PositionRotation Tag="DATA">
      <Position>
        <X>2242.73218</X>
        <Y>5022.74902</Y>
        <Z>7508.59961</Z>
      </Position>
      <Rotation>
        <X>6.08537149</X>
        <Y>0.0854094326</Y>
        <Z>6.27655983</Z>
      </Rotation>
    </PositionRotation>
  </Subrecords>
</Record>