<?xml version="1.0" encoding="utf-8"?>
<Record Tag="REFR">
  <Flags>0</Flags>
  <FormID ID="0C00CDD3">REFR - 0C00CDD3</FormID>
  <FormVersion>15</FormVersion>
  <CompressionCorrupted>false</CompressionCorrupted>
  <Subrecords>
    <Base Tag="NAME">
      <Reference ID="0013B2C3">NVHydra</Reference>
    </Base>
    <PositionRotation Tag="DATA">
      <Position>
        <X>21363.7637</X>
        <Y>-76607.2969</Y>
        <Z>12147.6094</Z>
      </Position>
      <Rotation>
        <X>0.0690818802</X>
        <Y>0.0172473434</Y>
        <Z>6.07212973</Z>
      </Rotation>
    </PositionRotation>
  </Subrecords>
</Record>