<?xml version="1.0" encoding="utf-8"?>
<Record Tag="REFR">
  <Flags>0</Flags>
  <FormID ID="0C01297C">REFR - 0C01297C</FormID>
  <FormVersion>15</FormVersion>
  <CompressionCorrupted>false</CompressionCorrupted>
  <Subrecords>
    <Base Tag="NAME">
      <Reference ID="000F9DC5">v22Fern</Reference>
    </Base>
    <PositionRotation Tag="DATA">
      <Position>
        <X>3524.16675</X>
        <Y>465.858856</Y>
        <Z>7999.92627</Z>
      </Position>
      <Rotation>
        <X>0</X>
        <Y>0</Y>
        <Z>6.10357714</Z>
      </Rotation>
    </PositionRotation>
  </Subrecords>
</Record>