<?xml version="1.0" encoding="utf-8"?>
<Record Tag="REFR">
  <Flags>0</Flags>
  <FormID ID="0601B004">REFR - 0601B004</FormID>
  <FormVersion>15</FormVersion>
  <CompressionCorrupted>false</CompressionCorrupted>
  <Subrecords>
    <Base Tag="NAME">
      <Reference ID="0C00CD2D">TTWFungus03ACTIVATOR</Reference>
    </Base>
    <Scale Tag="XSCL">1.17999995</Scale>
    <PositionRotation Tag="DATA">
      <Position>
        <X>109836.266</X>
        <Y>-47107.5547</Y>
        <Z>12336.0654</Z>
      </Position>
      <Rotation>
        <X>0.116027743</X>
        <Y>6.25798082</Y>
        <Z>0.417795181</Z>
      </Rotation>
    </PositionRotation>
  </Subrecords>
</Record>