<?xml version="1.0" encoding="utf-8"?>
<Record Tag="REFR">
  <Flags>0</Flags>
  <FormID ID="0C013F58">REFR - 0C013F58</FormID>
  <FormVersion>15</FormVersion>
  <CompressionCorrupted>false</CompressionCorrupted>
  <Subrecords>
    <Base Tag="NAME">
      <Reference ID="0007DF8A">DinerBooth02TableR</Reference>
    </Base>
    <PositionRotation Tag="DATA">
      <Position>
        <X>1377.54761</X>
        <Y>-343.608154</Y>
        <Z>12634.9072</Z>
      </Position>
      <Rotation>
        <X>0.0200014729</X>
        <Y>0.00999724586</Y>
        <Z>4.41588354</Z>
      </Rotation>
    </PositionRotation>
  </Subrecords>
</Record>