<?xml version="1.0" encoding="utf-8"?>
<Record Tag="LSCR">
  <Flags>0</Flags>
  <FormID ID="0007C344">PerkLoadScreen22</FormID>
  <FormVersion>15</FormVersion>
  <CompressionCorrupted>false</CompressionCorrupted>
  <Subrecords>
    <EditorID Tag="EDID">PerkLoadScreen22</EditorID>
    <Icon>
      <Large Tag="ICON">interface\loading\loading_bulletinboard07.dds</Large>
      <Small Tag="MICO"></Small>
    </Icon>
    <Description Tag="DESC">With the Lead Belly perk, you take 50% less radiation every time you drink from an irradiated water source.</Description>
    <LoadScreenType Tag="WMI1">
      <Reference ID="00166D58">StandardLoadingTip</Reference>
    </LoadScreenType>
  </Subrecords>
</Record>