<?xml version="1.0" encoding="utf-8"?>
<Record Tag="REFR">
  <Flags>0</Flags>
  <FormID ID="0C0181C6">REFR - 0C0181C6</FormID>
  <FormVersion>15</FormVersion>
  <CompressionCorrupted>false</CompressionCorrupted>
  <Subrecords>
    <Base Tag="NAME">
      <Reference ID="0015EB41">XanderRootPlant</Reference>
    </Base>
    <Scale Tag="XSCL">1.05999994</Scale>
    <PositionRotation Tag="DATA">
      <Position>
        <X>-41408</X>
        <Y>-58964.0586</Y>
        <Z>15033.2539</Z>
      </Position>
      <Rotation>
        <X>0</X>
        <Y>0</Y>
        <Z>1.664428</Z>
      </Rotation>
    </PositionRotation>
  </Subrecords>
</Record>