<?xml version="1.0" encoding="utf-8"?>
<Record Tag="REFR">
  <Flags>0</Flags>
  <FormID ID="0C0043CB">REFR - 0C0043CB</FormID>
  <FormVersion>15</FormVersion>
  <CompressionCorrupted>false</CompressionCorrupted>
  <Subrecords>
    <Base Tag="NAME">
      <Reference ID="000F1E4C">dlc04sodacup02</Reference>
    </Base>
    <PositionRotation Tag="DATA">
      <Position>
        <X>3255.09668</X>
        <Y>2474.45654</Y>
        <Z>6732.02002</Z>
      </Position>
      <Rotation>
        <X>1.43415105</X>
        <Y>0.753263175</Y>
        <Z>0.760288119</Z>
      </Rotation>
    </PositionRotation>
  </Subrecords>
</Record>