<?xml version="1.0" encoding="utf-8"?>
<Record Tag="REFR">
  <Flags>0</Flags>
  <FormID ID="0C003BE5">REFR - 0C003BE5</FormID>
  <FormVersion>15</FormVersion>
  <CompressionCorrupted>false</CompressionCorrupted>
  <Subrecords>
    <Base Tag="NAME">
      <Reference ID="0607E29F">UndNRmFreeCol02a</Reference>
    </Base>
    <Scale Tag="XSCL">2.27999997</Scale>
    <PositionRotation Tag="DATA">
      <Position>
        <X>3185.81641</X>
        <Y>2402.21948</Y>
        <Z>6720</Z>
      </Position>
      <Rotation>
        <X>6.18268728</X>
        <Y>6.18368912</Y>
        <Z>0.0100164441</Z>
      </Rotation>
    </PositionRotation>
  </Subrecords>
</Record>