<?xml version="1.0" encoding="utf-8"?>
<Record Tag="REFR">
  <Flags>0</Flags>
  <FormID ID="0C0046CC">REFR - 0C0046CC</FormID>
  <FormVersion>15</FormVersion>
  <CompressionCorrupted>false</CompressionCorrupted>
  <Subrecords>
    <Base Tag="NAME">
      <Reference ID="00022103">NukaColaBottle</Reference>
    </Base>
    <PositionRotation Tag="DATA">
      <Position>
        <X>3970.73145</X>
        <Y>3599.91504</Y>
        <Z>6736.12012</Z>
      </Position>
      <Rotation>
        <X>1.34815335</X>
        <Y>0.165422305</Y>
        <Z>5.12104368</Z>
      </Rotation>
    </PositionRotation>
  </Subrecords>
</Record>