<?xml version="1.0" encoding="utf-8"?>
<Record Tag="REFR">
  <Flags>0</Flags>
  <FormID ID="0C003CA3">REFR - 0C003CA3</FormID>
  <FormVersion>15</FormVersion>
  <CompressionCorrupted>false</CompressionCorrupted>
  <Subrecords>
    <Base Tag="NAME">
      <Reference ID="0008F8B5">SubDiningChair</Reference>
    </Base>
    <PositionRotation Tag="DATA">
      <Position>
        <X>4271.94043</X>
        <Y>783.893372</Y>
        <Z>6771</Z>
      </Position>
      <Rotation>
        <X>4.81996918</X>
        <Y>0.210029438</Y>
        <Z>3.58880877</Z>
      </Rotation>
    </PositionRotation>
  </Subrecords>
</Record>