<?xml version="1.0" encoding="utf-8"?>
<Record Tag="REFR">
  <Flags>0</Flags>
  <FormID ID="0C0043AF">REFR - 0C0043AF</FormID>
  <FormVersion>15</FormVersion>
  <CompressionCorrupted>false</CompressionCorrupted>
  <Subrecords>
    <Base Tag="NAME">
      <Reference ID="00022103">NukaColaBottle</Reference>
    </Base>
    <PositionRotation Tag="DATA">
      <Position>
        <X>3969.47266</X>
        <Y>2857.94604</Y>
        <Z>6740.6665</Z>
      </Position>
      <Rotation>
        <X>4.36829567</X>
        <Y>0.00833045691</Y>
        <Z>1.66321146</Z>
      </Rotation>
    </PositionRotation>
  </Subrecords>
</Record>