<?xml version="1.0" encoding="utf-8"?>
<Record Tag="REFR">
  <Flags>0</Flags>
  <FormID ID="0C0046D9">REFR - 0C0046D9</FormID>
  <FormVersion>15</FormVersion>
  <CompressionCorrupted>false</CompressionCorrupted>
  <Subrecords>
    <Base Tag="NAME">
      <Reference ID="0005B6CE">WhiskeyBottle01Empty01</Reference>
    </Base>
    <PositionRotation Tag="DATA">
      <Position>
        <X>4325.8623</X>
        <Y>4040.32666</Y>
        <Z>6741.16309</Z>
      </Position>
      <Rotation>
        <X>2.02414727</X>
        <Y>5.68263865</Y>
        <Z>6.09670401</Z>
      </Rotation>
    </PositionRotation>
  </Subrecords>
</Record>