<?xml version="1.0" encoding="utf-8"?>
<Record Tag="REFR">
  <Flags>0</Flags>
  <FormID ID="0C004697">REFR - 0C004697</FormID>
  <FormVersion>15</FormVersion>
  <CompressionCorrupted>false</CompressionCorrupted>
  <Subrecords>
    <Base Tag="NAME">
      <Reference ID="0005B6CA">TinCan02</Reference>
    </Base>
    <PositionRotation Tag="DATA">
      <Position>
        <X>2991.28101</X>
        <Y>4766.00439</Y>
        <Z>6869.27051</Z>
      </Position>
      <Rotation>
        <X>4.71361399</X>
        <Y>5.14203691</Y>
        <Z>1.04452717</Z>
      </Rotation>
    </PositionRotation>
  </Subrecords>
</Record>