<?xml version="1.0" encoding="utf-8"?>
<Record Tag="REFR">
  <Flags>0</Flags>
  <FormID ID="0C0045A6">REFR - 0C0045A6</FormID>
  <FormVersion>15</FormVersion>
  <CompressionCorrupted>false</CompressionCorrupted>
  <Subrecords>
    <Base Tag="NAME">
      <Reference ID="00020525">NukaVendingMachine</Reference>
    </Base>
    <Scale Tag="XSCL">0.150000006</Scale>
    <PositionRotation Tag="DATA">
      <Position>
        <X>5059.74219</X>
        <Y>2349.19165</Y>
        <Z>6864.5874</Z>
      </Position>
      <Rotation>
        <X>4.80484772</X>
        <Y>0.697894335</Y>
        <Z>0.0595139824</Z>
      </Rotation>
    </PositionRotation>
  </Subrecords>
</Record>