<?xml version="1.0" encoding="utf-8"?>
<Record Tag="REFR">
  <Flags>0</Flags>
  <FormID ID="0C0043E2">REFR - 0C0043E2</FormID>
  <FormVersion>15</FormVersion>
  <CompressionCorrupted>false</CompressionCorrupted>
  <Subrecords>
    <Base Tag="NAME">
      <Reference ID="000F1E4C">dlc04sodacup02</Reference>
    </Base>
    <PositionRotation Tag="DATA">
      <Position>
        <X>1898.51453</X>
        <Y>3572.17676</Y>
        <Z>6729.72217</Z>
      </Position>
      <Rotation>
        <X>4.52165079</X>
        <Y>0.624232709</Y>
        <Z>5.9703908</Z>
      </Rotation>
    </PositionRotation>
  </Subrecords>
</Record>