<?xml version="1.0" encoding="utf-8"?>
<Record Tag="REFR">
  <Flags>0</Flags>
  <FormID ID="0C00450D">REFR - 0C00450D</FormID>
  <FormVersion>15</FormVersion>
  <CompressionCorrupted>false</CompressionCorrupted>
  <Subrecords>
    <Base Tag="NAME">
      <Reference ID="000389C6">Telephone01</Reference>
    </Base>
    <PositionRotation Tag="DATA">
      <Position>
        <X>4749.7915</X>
        <Y>620.638245</Y>
        <Z>6796.05908</Z>
      </Position>
      <Rotation>
        <X>6.28275442</X>
        <Y>6.28216076</Y>
        <Z>2.68773365</Z>
      </Rotation>
    </PositionRotation>
  </Subrecords>
</Record>