<?xml version="1.0" encoding="utf-8"?>
<Record Tag="REFR">
  <Flags>0</Flags>
  <FormID ID="0C0046B0">REFR - 0C0046B0</FormID>
  <FormVersion>15</FormVersion>
  <CompressionCorrupted>false</CompressionCorrupted>
  <Subrecords>
    <Base Tag="NAME">
      <Reference ID="0005B6CA">TinCan02</Reference>
    </Base>
    <PositionRotation Tag="DATA">
      <Position>
        <X>4654.58691</X>
        <Y>4026.76929</Y>
        <Z>6759.49365</Z>
      </Position>
      <Rotation>
        <X>4.1286602</X>
        <Y>5.30613422</Y>
        <Z>5.46228361</Z>
      </Rotation>
    </PositionRotation>
  </Subrecords>
</Record>