<?xml version="1.0" encoding="utf-8"?>
<Record Tag="REFR">
  <Flags>0</Flags>
  <FormID ID="0C003D1E">REFR - 0C003D1E</FormID>
  <FormVersion>15</FormVersion>
  <CompressionCorrupted>false</CompressionCorrupted>
  <Subrecords>
    <Base Tag="NAME">
      <Reference ID="000AB475">ComputerOfficeChairRuined01R</Reference>
    </Base>
    <PositionRotation Tag="DATA">
      <Position>
        <X>1934.84326</X>
        <Y>4422.89795</Y>
        <Z>6756</Z>
      </Position>
      <Rotation>
        <X>0</X>
        <Y>0</Y>
        <Z>5.7123909</Z>
      </Rotation>
    </PositionRotation>
  </Subrecords>
</Record>