<?xml version="1.0" encoding="utf-8"?>
<Record Tag="REFR">
  <Flags>0</Flags>
  <FormID ID="0C0042B1">REFR - 0C0042B1</FormID>
  <FormVersion>15</FormVersion>
  <CompressionCorrupted>false</CompressionCorrupted>
  <Subrecords>
    <Base Tag="NAME">
      <Reference ID="0005B6CA">TinCan02</Reference>
    </Base>
    <PositionRotation Tag="DATA">
      <Position>
        <X>1035.90405</X>
        <Y>3335.30103</Y>
        <Z>6726.41016</Z>
      </Position>
      <Rotation>
        <X>4.68954611</X>
        <Y>5.63387394</Y>
        <Z>1.05754209</Z>
      </Rotation>
    </PositionRotation>
  </Subrecords>
</Record>